kojak/__init__.py
kojak/__main__.py
kojak/utils.py
kojak/tests/test_kojak.py
kojak-0.3.0.dist-info/AUTHORS
kojak-0.3.0.dist-info/METADATA
kojak-0.3.0.dist-info/WHEEL
kojak-0.3.0.dist-info/entry_points.txt
kojak-0.3.0.dist-info/pbr.json
kojak-0.3.0.dist-info/top_level.txt
kojak-0.3.0.dist-info/RECORD
