Metadata-Version: 2.1
Name: kojak
Version: 0.3.0
Summary: Python file analyzer
Home-page: https://github.com/4383/kojak/
Author: Hervé Beraud
Author-email: herveberaud.pro@gmail.com
License: MIT
Platform: UNKNOWN
Classifier: Development Status :: 5 - Production/Stable
Classifier: Intended Audience :: Information Technology
Classifier: License :: OSI Approved :: MIT License
Classifier: Operating System :: POSIX
Classifier: Programming Language :: Python
Classifier: Programming Language :: Python :: 3
Classifier: Programming Language :: Python :: 3.4
Classifier: Programming Language :: Python :: 3.5
Classifier: Programming Language :: Python :: 3.6
Requires: pbr
